test_package_balobinp/__init__.py
test_package_balobinp/hello.py
test_package_balobinp-1.0.0.dist-info/DESCRIPTION.rst
test_package_balobinp-1.0.0.dist-info/METADATA
test_package_balobinp-1.0.0.dist-info/RECORD
test_package_balobinp-1.0.0.dist-info/WHEEL
test_package_balobinp-1.0.0.dist-info/metadata.json
test_package_balobinp-1.0.0.dist-info/top_level.txt
