Metadata-Version: 2.0
Name: test-package-balobinp
Version: 1.0.0
Summary: Just a teat package
Home-page: UNKNOWN
Author: Pavel Balobin
Author-email: office@realpython.com
License: MIT
Platform: UNKNOWN
Classifier: License :: OSI Approved :: MIT License
Classifier: Programming Language :: Python
Classifier: Programming Language :: Python :: 2
Classifier: Programming Language :: Python :: 3
Requires-Dist: pandas
